{"index": 153, "constant": true, "user": "danikstarik", "models": ["Heldt2012 - Influenza Virus Replication", "https://www.ebi.ac.uk/biomodels-main/BIOMD0000000463"], "tags": ["species_9", "species_3", "species_17", "parameter_4", "species_12", "vRNP", "species_5", "species_14", "virus", "parameter_29", "species_4", "species_15", "species_34", "parameter_27", "species_23", "viral", "parameter_28", "Influenza", "virus replication", "species_26", "parameter_16", "mammalian cell", "Infection", "endocytosis", "life cycle", "parameter_7", "species_19", "species_21", "cRNA", "species_20", "species_16", "species_22", "species_25", "species_24", "species_27", "species_31"], "units": "", "symbol": "parameter_2", "notes": "compartment_1 * (parameter_2 * species_3 * species_4 - parameter_4 * species_5)  ;  compartment_1 * parameter_27 * species_26  ;  compartment_1 * parameter_29 * species_27  ;  compartment_1 * parameter_28 * species_26  ;  compartment_1 * parameter_20 * species_9  ;  compartment_1 * parameter_22 * species_12  ;  compartment_1 * parameter_22 * species_19  ;  compartment_1 * parameter_20 * species_17  ;  compartment_1 * parameter_20 * species_15  ;  compartment_1 * parameter_20 * species_16  ;  compartment_1 * parameter_21 * species_20  ;  compartment_1 * parameter_21 * species_21  ;  compartment_1 * parameter_21 * species_22  ;  compartment_1 * parameter_21 * species_23  ;  compartment_1 * parameter_21 * species_24  ;  compartment_1 * parameter_21 * species_25  ;  compartment_1 * parameter_21 * species_26  ;  compartment_1 * parameter_21 * species_27  ;  parameter_9 / parameter_24  ;  parameter_2 / parameter_48  ;  (1 - parameter_23) / parameter_23 * parameter_6  ;  parameter_9 / parameter_24 * (1 - parameter_25)  ;  parameter_9 / parameter_24 * parameter_25  ;  parameter_9 / parameter_24 * parameter_26  ;  ", "value": 0.000455, "name": "parameter_2 parameter_29"}